odoo8_addon_portal_welcome_email_template-8.0.1.0.0.99.dev8-py2.7-nspkg.pth
odoo8_addon_portal_welcome_email_template-8.0.1.0.0.99.dev8.dist-info/DESCRIPTION.rst
odoo8_addon_portal_welcome_email_template-8.0.1.0.0.99.dev8.dist-info/METADATA
odoo8_addon_portal_welcome_email_template-8.0.1.0.0.99.dev8.dist-info/RECORD
odoo8_addon_portal_welcome_email_template-8.0.1.0.0.99.dev8.dist-info/WHEEL
odoo8_addon_portal_welcome_email_template-8.0.1.0.0.99.dev8.dist-info/metadata.json
odoo8_addon_portal_welcome_email_template-8.0.1.0.0.99.dev8.dist-info/namespace_packages.txt
odoo8_addon_portal_welcome_email_template-8.0.1.0.0.99.dev8.dist-info/top_level.txt
odoo_addons/portal_welcome_email_template/README.rst
odoo_addons/portal_welcome_email_template/__init__.py
odoo_addons/portal_welcome_email_template/__openerp__.py
odoo_addons/portal_welcome_email_template/data/email_template_data.xml
odoo_addons/portal_welcome_email_template/i18n/de.po
odoo_addons/portal_welcome_email_template/i18n/es.po
odoo_addons/portal_welcome_email_template/i18n/fr.po
odoo_addons/portal_welcome_email_template/i18n/portal_welcome_email_template.pot
odoo_addons/portal_welcome_email_template/i18n/sl.po
odoo_addons/portal_welcome_email_template/static/description/icon.png
odoo_addons/portal_welcome_email_template/tests/__init__.py
odoo_addons/portal_welcome_email_template/tests/test_portal_welcome_email_template.py
odoo_addons/portal_welcome_email_template/wizards/__init__.py
odoo_addons/portal_welcome_email_template/wizards/portal_wizard.py
